{
  "name": "OHR.Bavljenac_ZH-CN1739905750",
  "urlbase": "/th?id=OHR.Bavljenac_ZH-CN1739905750",
  "copyright_cn": "像巨大指纹一样的Bavljenac岛，克罗地亚 (© Julien Duval/Amazing Aerial Agency)",
  "copyrightlink": "/search?q=%e5%85%8b%e7%bd%97%e5%9c%b0%e4%ba%9a&form=hpcapt&mkt=zh-cn",
  "desc": "Of the 1,246 islands on Croatia's fragmented coast, the unique isle of Bavljenac might be the most identifiable. It's nicknamed 'Fingerprint Island' for its miles of dry-stone walls that look like the whorled ridges of a human fingerprint. The tiny, uninhabited landmass in the Adriatic Sea was once an agricultural center. In the 19th century—the heyday of Croatian wine production— farmers from the nearest populated island built the winding walls on Bavljenac to protect olive trees and grapevines from the  winds blowing in from the Adriatic.",
  "copyright": "Bavljenac Island, Croatia (© Julien Duval/Amazing Aerial Agency)",
  "raw_size": "4793x2696",
  "url": {
    "UHD": "https://www.bing.com/th?id=OHR.Bavljenac_ZH-CN1739905750_UHD.jpg",
    "1920x1080": "https://www.bing.com/th?id=OHR.Bavljenac_ZH-CN1739905750_1920x1080.jpg",
    "1024x768": "https://www.bing.com/th?id=OHR.Bavljenac_ZH-CN1739905750_1024x768.jpg",
    "1366x768": "https://www.bing.com/th?id=OHR.Bavljenac_ZH-CN1739905750_1366x768.jpg",
    "800x480": "https://www.bing.com/th?id=OHR.Bavljenac_ZH-CN1739905750_800x480.jpg",
    "1080x1920": "https://www.bing.com/th?id=OHR.Bavljenac_ZH-CN1739905750_1080x1920.jpg",
    "480x800": "https://www.bing.com/th?id=OHR.Bavljenac_ZH-CN1739905750_480x800.jpg"
  },
  "telegram": {
    "archive": {
      "UHD": {
        "message_id": 2513,
        "file_id": "BQACAgUAAx0EUeHgWwACCdFhdRKvilbZREjQb4_Mri0V4QwPugACxAMAAhLWqFesUw7rPb73RSEE"
      },
      "1920x1080": {
        "message_id": 2514,
        "file_id": "BQACAgUAAx0EUeHgWwACCdJhdRKwgqKuguEYCm83Hs5M0UzMDQACxQMAAhLWqFdruFVImRbJOSEE"
      },
      "1024x768": {
        "message_id": 2515,
        "file_id": "BQACAgUAAx0EUeHgWwACCdNhdRKyweAqFEE8qELUjHDd_2lrbQACxgMAAhLWqFe8scgq79WTMyEE"
      },
      "1366x768": {
        "message_id": 2516,
        "file_id": "BQACAgUAAx0EUeHgWwACCdRhdRKzZJSebB3LZ96-Itm2FkiyhAACxwMAAhLWqFeykzBexppL1CEE"
      },
      "800x480": {
        "message_id": 2517,
        "file_id": "BQACAgUAAx0EUeHgWwACCdVhdRK1_vbsRypcqJq4Huk4kFGgxgACyAMAAhLWqFc7LSvq9sDEHiEE"
      },
      "1080x1920": {
        "message_id": 2518,
        "file_id": "BQACAgUAAx0EUeHgWwACCdZhdRK28Y_rPmMylUkNkBAK3fz8LQACyQMAAhLWqFeQkhzhTYJaVCEE"
      },
      "480x800": {
        "message_id": 2519,
        "file_id": "BQACAgUAAx0EUeHgWwACCddhdRK4JNeiMootwZki_6RUrr09AQACygMAAhLWqFePBsLAqniOOCEE"
      }
    },
    "photo": [
      {
        "file_id": "AgACAgUAAx0ESGLKMAACAUJhdRK5MOHBjYtCsmiIxxy_FPi6QQAClrAxG3eEqVcdYjv37LNQAwEAAwIAA3MAAyEE",
        "file_unique_id": "AQADlrAxG3eEqVd4",
        "file_size": 1342,
        "width": 90,
        "height": 51
      },
      {
        "file_id": "AgACAgUAAx0ESGLKMAACAUJhdRK5MOHBjYtCsmiIxxy_FPi6QQAClrAxG3eEqVcdYjv37LNQAwEAAwIAA20AAyEE",
        "file_unique_id": "AQADlrAxG3eEqVdy",
        "file_size": 29340,
        "width": 320,
        "height": 180
      },
      {
        "file_id": "AgACAgUAAx0ESGLKMAACAUJhdRK5MOHBjYtCsmiIxxy_FPi6QQAClrAxG3eEqVcdYjv37LNQAwEAAwIAA3gAAyEE",
        "file_unique_id": "AQADlrAxG3eEqVd9",
        "file_size": 174089,
        "width": 800,
        "height": 450
      },
      {
        "file_id": "AgACAgUAAx0ESGLKMAACAUJhdRK5MOHBjYtCsmiIxxy_FPi6QQAClrAxG3eEqVcdYjv37LNQAwEAAwIAA3cAAyEE",
        "file_unique_id": "AQADlrAxG3eEqVd8",
        "file_size": 343616,
        "width": 1920,
        "height": 1080
      },
      {
        "file_id": "AgACAgUAAx0ESGLKMAACAUJhdRK5MOHBjYtCsmiIxxy_FPi6QQAClrAxG3eEqVcdYjv37LNQAwEAAwIAA3kAAyEE",
        "file_unique_id": "AQADlrAxG3eEqVd-",
        "file_size": 438454,
        "width": 1280,
        "height": 720
      }
    ]
  }
}