{
  "name": "OHR.MayonVolcano_ZH-CN0183039911",
  "urlbase": "/th?id=OHR.MayonVolcano_ZH-CN0183039911",
  "copyright_cn": "菲律宾马荣山的火山口冒烟 (© Per-Andre Hoffmann/Cavan)",
  "copyrightlink": "/search?q=%e9%a9%ac%e8%8d%a3%e7%81%ab%e5%b1%b1&form=hpcapt&mkt=zh-cn",
  "desc": "How far would you have to travel for the 'perfect cone'? Well, probably not too far if you're talking ice cream. But if volcanoes are what you're looking for, you'll have to make your way to Mount Mayon on the Philippine island of Luzon. The glowing lava you see is on the tip of the world's most perfectly shaped, symmetrical volcanic cone, which formed after years of eruptions from what is still an active stratovolcano. Mount Mayon has erupted dozens of times in the past 400 years, and there was a significant eruption as recently as 2018. Even this year, smaller white steam plume emissions and faint crater glow are sometimes visible. Mayon is the most active volcano in an island nation full of active volcanos, and is located inside the UNESCO Albay Biosphere Reserve, as well as the Philippine's Mayon Volcano Natural Park. Despite its active status, tourists still flock to the park to view the unique beauty of this cone shaped spectacle.",
  "copyright": "Crater glow from Mount Mayon in the Philippines (© Per-Andre Hoffmann/Cavan)",
  "raw_size": "7127x4009",
  "url": {
    "UHD": "https://www.bing.com/th?id=OHR.MayonVolcano_ZH-CN0183039911_UHD.jpg",
    "1920x1080": "https://www.bing.com/th?id=OHR.MayonVolcano_ZH-CN0183039911_1920x1080.jpg",
    "1024x768": "https://www.bing.com/th?id=OHR.MayonVolcano_ZH-CN0183039911_1024x768.jpg",
    "1366x768": "https://www.bing.com/th?id=OHR.MayonVolcano_ZH-CN0183039911_1366x768.jpg",
    "800x480": "https://www.bing.com/th?id=OHR.MayonVolcano_ZH-CN0183039911_800x480.jpg",
    "1080x1920": "https://www.bing.com/th?id=OHR.MayonVolcano_ZH-CN0183039911_1080x1920.jpg",
    "480x800": "https://www.bing.com/th?id=OHR.MayonVolcano_ZH-CN0183039911_480x800.jpg"
  },
  "telegram": {
    "archive": {
      "UHD": {
        "message_id": 2073,
        "file_id": "BQACAgUAAx0EUeHgWwACCBlhLJArtgxutE-8m0ACLjMiAAH5YgEAAnsDAALYQGlVCsqoMESjsWAgBA"
      },
      "1920x1080": {
        "message_id": 2074,
        "file_id": "BQACAgUAAx0EUeHgWwACCBphLJAvM3fR_eYLBxByalOH2EwYGQACfAMAAthAaVWnL65k3MS-YyAE"
      },
      "1024x768": {
        "message_id": 2075,
        "file_id": "BQACAgUAAx0EUeHgWwACCBthLJAwiRmWj1pHAmUzc2rNQbFi1wACfQMAAthAaVWQD-ASPKqUVSAE"
      },
      "1366x768": {
        "message_id": 2076,
        "file_id": "BQACAgUAAx0EUeHgWwACCBxhLJAyZW4WTlYbMhO-nbLjgInskwACfgMAAthAaVVpDKCr1MHVtyAE"
      },
      "800x480": {
        "message_id": 2077,
        "file_id": "BQACAgUAAx0EUeHgWwACCB1hLJAziHJEIbYgpsCbbt3JqupLnQACfwMAAthAaVWH2TiLZr2FYiAE"
      },
      "1080x1920": {
        "message_id": 2078,
        "file_id": "BQACAgUAAx0EUeHgWwACCB5hLJA1eSzYhs5wSb-mf1NLNIYvOgACgAMAAthAaVWAidhDX3rgiyAE"
      },
      "480x800": {
        "message_id": 2079,
        "file_id": "BQACAgUAAx0EUeHgWwACCB9hLJA2dxxgRvWDijmBAAFSMa8k_fQAAoEDAALYQGlVaC_S131TI2ogBA"
      }
    },
    "photo": [
      {
        "file_id": "AgACAgUAAx0ESGLKMAACAQthLJA5d4cgbTmRF7pF2PrddRbPIgAC5K0xG6NYYVVKfCPTD28vWAEAAwIAA3MAAyAE",
        "file_unique_id": "AQAD5K0xG6NYYVV4",
        "file_size": 775,
        "width": 90,
        "height": 51
      },
      {
        "file_id": "AgACAgUAAx0ESGLKMAACAQthLJA5d4cgbTmRF7pF2PrddRbPIgAC5K0xG6NYYVVKfCPTD28vWAEAAwIAA20AAyAE",
        "file_unique_id": "AQAD5K0xG6NYYVVy",
        "file_size": 6002,
        "width": 320,
        "height": 180
      },
      {
        "file_id": "AgACAgUAAx0ESGLKMAACAQthLJA5d4cgbTmRF7pF2PrddRbPIgAC5K0xG6NYYVVKfCPTD28vWAEAAwIAA3gAAyAE",
        "file_unique_id": "AQAD5K0xG6NYYVV9",
        "file_size": 23704,
        "width": 800,
        "height": 450
      },
      {
        "file_id": "AgACAgUAAx0ESGLKMAACAQthLJA5d4cgbTmRF7pF2PrddRbPIgAC5K0xG6NYYVVKfCPTD28vWAEAAwIAA3kAAyAE",
        "file_unique_id": "AQAD5K0xG6NYYVV-",
        "file_size": 56430,
        "width": 1280,
        "height": 720
      },
      {
        "file_id": "AgACAgUAAx0ESGLKMAACAQthLJA5d4cgbTmRF7pF2PrddRbPIgAC5K0xG6NYYVVKfCPTD28vWAEAAwIAA3cAAyAE",
        "file_unique_id": "AQAD5K0xG6NYYVV8",
        "file_size": 143861,
        "width": 1920,
        "height": 1080
      }
    ]
  }
}