{
  "name": "OHR.LammasDay_ZH-CN4229387191",
  "urlbase": "/th?id=OHR.LammasDay_ZH-CN4229387191",
  "copyright_cn": "东洛锡安的金黄麦田，苏格兰 (© Scott Masterton/plainpicture)",
  "copyrightlink": "/search?q=%e4%b8%9c%e6%b4%9b%e9%94%a1%e5%ae%89&form=hpcapt&mkt=zh-cn",
  "desc": "Today, we're in the 'Garden of Scotland,' better known as the East Lothian region, to pay homage to the area's agricultural roots on Lammas Day. Also known as Loaf Mass Day, it's an observance that marks the beginning of the harvest season and is traditionally celebrated on August 1. The holiday is descended from the ancient British tradition known during the Middle Ages as the Gule of August and was gradually incorporated into the Christian liturgy celebrating Holy Communion. It gets its name from loaves of bread baked from the first harvested grain of the season each year.",
  "copyright": "Barley field in East Lothian, Scotland (© Scott Masterton/plainpicture)",
  "raw_size": "3817x2147",
  "url": {
    "UHD": "https://www.bing.com/th?id=OHR.LammasDay_ZH-CN4229387191_UHD.jpg",
    "1920x1080": "https://www.bing.com/th?id=OHR.LammasDay_ZH-CN4229387191_1920x1080.jpg",
    "1024x768": "https://www.bing.com/th?id=OHR.LammasDay_ZH-CN4229387191_1024x768.jpg",
    "1366x768": "https://www.bing.com/th?id=OHR.LammasDay_ZH-CN4229387191_1366x768.jpg",
    "800x480": "https://www.bing.com/th?id=OHR.LammasDay_ZH-CN4229387191_800x480.jpg",
    "1080x1920": "https://www.bing.com/th?id=OHR.LammasDay_ZH-CN4229387191_1080x1920.jpg",
    "480x800": "https://www.bing.com/th?id=OHR.LammasDay_ZH-CN4229387191_480x800.jpg"
  },
  "telegram": {
    "archive": {
      "UHD": {
        "message_id": 1841,
        "file_id": "BQACAgUAAx0EUeHgWwACBzFhBlS5agABsqBncjrwYa57J3aYhgQAAnYEAAKCnDFUxUvOGp22_h8gBA"
      },
      "1920x1080": {
        "message_id": 1842,
        "file_id": "BQACAgUAAx0EUeHgWwACBzJhBlS7EatMrO5-UrjK4wNG3N1XjgACdwQAAoKcMVSVfZ5_2BemuyAE"
      },
      "1024x768": {
        "message_id": 1843,
        "file_id": "BQACAgUAAx0EUeHgWwACBzNhBlS9aEVoq1sXxTiEHDn-1vmYKwACeAQAAoKcMVQ3IT_dgDNcWiAE"
      },
      "1366x768": {
        "message_id": 1844,
        "file_id": "BQACAgUAAx0EUeHgWwACBzRhBlS_5cxCiuFuRPsp9gJxbA3n7gACeQQAAoKcMVSUTYAmDSXiLCAE"
      },
      "800x480": {
        "message_id": 1845,
        "file_id": "BQACAgUAAx0EUeHgWwACBzVhBlTArR-6BjuBU7xZMJafLxqbxAACegQAAoKcMVTkryCiuLXU3iAE"
      },
      "1080x1920": {
        "message_id": 1846,
        "file_id": "BQACAgUAAx0EUeHgWwACBzZhBlTCWcZObb7eEy7ZK-_Zsy0AAXsAAnsEAAKCnDFUvkxRgwGa2k0gBA"
      },
      "480x800": {
        "message_id": 1847,
        "file_id": "BQACAgUAAx0EUeHgWwACBzdhBlTEE23jPQbZisYO6xbbR9SBXwACfAQAAoKcMVSuQ1dqkEv3UiAE"
      }
    },
    "photo": [
      {
        "file_id": "AgACAgUAAx0ESGLKMAAD7mEGVMfVugbZJC5SWcCWYdE4BRcfAAKeqzEb6HUxVG8kJNqNhfyTAQADAgADcwADIAQ",
        "file_unique_id": "AQADnqsxG-h1MVR4",
        "file_size": 1274,
        "width": 90,
        "height": 51
      },
      {
        "file_id": "AgACAgUAAx0ESGLKMAAD7mEGVMfVugbZJC5SWcCWYdE4BRcfAAKeqzEb6HUxVG8kJNqNhfyTAQADAgADbQADIAQ",
        "file_unique_id": "AQADnqsxG-h1MVRy",
        "file_size": 18616,
        "width": 320,
        "height": 180
      },
      {
        "file_id": "AgACAgUAAx0ESGLKMAAD7mEGVMfVugbZJC5SWcCWYdE4BRcfAAKeqzEb6HUxVG8kJNqNhfyTAQADAgADeAADIAQ",
        "file_unique_id": "AQADnqsxG-h1MVR9",
        "file_size": 91800,
        "width": 800,
        "height": 450
      },
      {
        "file_id": "AgACAgUAAx0ESGLKMAAD7mEGVMfVugbZJC5SWcCWYdE4BRcfAAKeqzEb6HUxVG8kJNqNhfyTAQADAgADeQADIAQ",
        "file_unique_id": "AQADnqsxG-h1MVR-",
        "file_size": 223369,
        "width": 1280,
        "height": 720
      },
      {
        "file_id": "AgACAgUAAx0ESGLKMAAD7mEGVMfVugbZJC5SWcCWYdE4BRcfAAKeqzEb6HUxVG8kJNqNhfyTAQADAgADdwADIAQ",
        "file_unique_id": "AQADnqsxG-h1MVR8",
        "file_size": 344019,
        "width": 1920,
        "height": 1080
      }
    ]
  }
}