{
  "name": "OHR.EileanDonanDawn_ZH-CN0383017858",
  "urlbase": "/th?id=OHR.EileanDonanDawn_ZH-CN0383017858",
  "copyright_cn": "艾琳多南堡，苏格兰高地 (© VisualCommunications/Getty Images)",
  "copyrightlink": "/search?q=%e8%89%be%e7%90%b3%e5%a4%9a%e5%8d%97%e5%a0%a1&form=hpcapt&mkt=zh-cn",
  "desc": "With sweeping views of fjords, mountains, and the sea, this is possibly one of the best places in the world to rest when you are on the road. Ureddplassen Rest Area, also known as Uredd Rest Area, is located on a section of the National Scenic Road Helgelandskysten in Norway. Characterized by its minimalist, futuristic architecture and breathtaking scenery all around, Ureddplassen offers a visual experience like no other. It has marble benches and steps leading out to the open sea, and a wave-shaped public restroom with frosted glass that lights up beautifully in the dark. Since its unveiling, the rest area has quickly become a popular tourist destination that draws in both locals and visitors. Here, they can also witness the midnight sun in the summer and feast their eyes on the northern lights in winter.",
  "copyright": "Ureddplassen, a rest area on the Helgelandskysten Norwegian Scenic Route, Norway (© Eyesite/Alamy)",
  "raw_size": "3929x2211",
  "url": {
    "UHD": "https://www.bing.com/th?id=OHR.EileanDonanDawn_ZH-CN0383017858_UHD.jpg",
    "1920x1080": "https://www.bing.com/th?id=OHR.EileanDonanDawn_ZH-CN0383017858_1920x1080.jpg",
    "1024x768": "https://www.bing.com/th?id=OHR.EileanDonanDawn_ZH-CN0383017858_1024x768.jpg",
    "1366x768": "https://www.bing.com/th?id=OHR.EileanDonanDawn_ZH-CN0383017858_1366x768.jpg",
    "800x480": "https://www.bing.com/th?id=OHR.EileanDonanDawn_ZH-CN0383017858_800x480.jpg",
    "1080x1920": "https://www.bing.com/th?id=OHR.EileanDonanDawn_ZH-CN0383017858_1080x1920.jpg",
    "480x800": "https://www.bing.com/th?id=OHR.EileanDonanDawn_ZH-CN0383017858_480x800.jpg"
  },
  "telegram": {
    "archive": {
      "UHD": {
        "message_id": 6292,
        "file_id": "BQACAgUAAx0EUeHgWwACGJRj41a1DIFh7zpWO4wKntp_GIKxLwAC-QcAAutPIVfpm4Oq-iWGpC4E"
      },
      "1920x1080": {
        "message_id": 6293,
        "file_id": "BQACAgUAAx0EUeHgWwACGJVj41a3MUmZoBAvuaCwFaAQS6FMRgAC-gcAAutPIVdzf95QfEoVsy4E"
      },
      "1024x768": {
        "message_id": 6294,
        "file_id": "BQACAgUAAx0EUeHgWwACGJZj41a4JzW9aEjzS2Uttb8rvWngvwAC-wcAAutPIVd6AAFJ7f2uWusuBA"
      },
      "1366x768": {
        "message_id": 6295,
        "file_id": "BQACAgUAAx0EUeHgWwACGJdj41a6w0TwT7SROwt-YUkWwII6HwAC_AcAAutPIVcrTNYmlS6Zzy4E"
      },
      "800x480": {
        "message_id": 6296,
        "file_id": "BQACAgUAAx0EUeHgWwACGJhj41a8aIetFVPGzSKA81WdcUokGQAC_QcAAutPIVdaa9nu6kW7ey4E"
      },
      "1080x1920": {
        "message_id": 6297,
        "file_id": "BQACAgUAAx0EUeHgWwACGJlj41a9RVPczEjqR7P10NDmAwt9cAAC_gcAAutPIVcXVxKRnxwzdi4E"
      },
      "480x800": {
        "message_id": 6298,
        "file_id": "BQACAgUAAx0EUeHgWwACGJpj41a_qZOtexFqE3U_0mg8lvTz6wAC_wcAAutPIVd4gw2t_iItgC4E"
      }
    },
    "photo": [
      {
        "file_id": "AgACAgUAAx0ESGLKMAACAxpj41bC475xSz8ceaQNR5HIDEFPjAACJLYxG9xHGVd7RjtLDB-G4AEAAwIAA3MAAy4E",
        "file_unique_id": "AQADJLYxG9xHGVd4",
        "file_size": 1151,
        "width": 90,
        "height": 51
      },
      {
        "file_id": "AgACAgUAAx0ESGLKMAACAxpj41bC475xSz8ceaQNR5HIDEFPjAACJLYxG9xHGVd7RjtLDB-G4AEAAwIAA20AAy4E",
        "file_unique_id": "AQADJLYxG9xHGVdy",
        "file_size": 14227,
        "width": 320,
        "height": 180
      },
      {
        "file_id": "AgACAgUAAx0ESGLKMAACAxpj41bC475xSz8ceaQNR5HIDEFPjAACJLYxG9xHGVd7RjtLDB-G4AEAAwIAA3gAAy4E",
        "file_unique_id": "AQADJLYxG9xHGVd9",
        "file_size": 67429,
        "width": 800,
        "height": 450
      },
      {
        "file_id": "AgACAgUAAx0ESGLKMAACAxpj41bC475xSz8ceaQNR5HIDEFPjAACJLYxG9xHGVd7RjtLDB-G4AEAAwIAA3kAAy4E",
        "file_unique_id": "AQADJLYxG9xHGVd-",
        "file_size": 162311,
        "width": 1280,
        "height": 720
      },
      {
        "file_id": "AgACAgUAAx0ESGLKMAACAxpj41bC475xSz8ceaQNR5HIDEFPjAACJLYxG9xHGVd7RjtLDB-G4AEAAwIAA3cAAy4E",
        "file_unique_id": "AQADJLYxG9xHGVd8",
        "file_size": 299292,
        "width": 1920,
        "height": 1080
      }
    ]
  }
}